gitspy/__init__.py
gitspy/_subprocess.py
gitspy/_version.py
gitspy/py.typed
gitspy-0.3.0.dist-info/LICENSE
gitspy-0.3.0.dist-info/WHEEL
gitspy-0.3.0.dist-info/METADATA
gitspy-0.3.0.dist-info/RECORD
