Metadata-Version: 2.1
Name: gitspy
Version: 0.3.0
Summary: Intuitive Git for Python
Home-page: https://pypi.org/project/gitspy/
License: MIT
Keywords: commandline,git,script,tree,wrapper
Author: jshwi
Author-email: stephen@jshwisolutions.com
Maintainer: jshwi
Maintainer-email: stephen@jshwisolutions.com
Requires-Python: >=3.8,<4.0
Classifier: License :: OSI Approved :: MIT License
Classifier: Programming Language :: Python :: 3
Classifier: Programming Language :: Python :: 3.8
Classifier: Programming Language :: Python :: 3.9
Classifier: Programming Language :: Python :: 3.10
Requires-Dist: spall (>=0,<1)
Project-URL: Documentation, https://gitspy.readthedocs.io/en/latest
Project-URL: Repository, https://github.com/jshwi/gitspy
